random_art/__init__.py
random_art/__metadata__.py
random_art/crypto.py
random_art/randomart.py
randomart-0.2.3.data/scripts/randomart.py
randomart-0.2.3.dist-info/LICENSE
randomart-0.2.3.dist-info/METADATA
randomart-0.2.3.dist-info/WHEEL
randomart-0.2.3.dist-info/top_level.txt
randomart-0.2.3.dist-info/RECORD
