Metadata-Version: 2.1
Name: randomart
Version: 0.2.3
Summary: Generate ASCII randomart by hashing input with BLAKE2b and using an adapted drunken bishop alogirthm.
Home-page: https://github.com/ansemjo/randomart
Author: Anton Semjonov
Author-email: anton@semjonov.de
License: MIT
Keywords: randomart drunken bishop openssh blake2b blake2 hash comparison
Platform: UNKNOWN
Requires-Python: >3.5
Requires-Dist: numpy
